easyjsoner/__init__.py
easyjsoner/jsoner.py
easyjsoner-0.0.2.dist-info/METADATA
easyjsoner-0.0.2.dist-info/WHEEL
easyjsoner-0.0.2.dist-info/licenses/LICENSE
easyjsoner-0.0.2.dist-info/RECORD
