Metadata-Version: 2.4
Name: easyjsoner
Version: 0.0.2
Summary: The simplest module for quick work with json files
Author-email: qxuwll <ivanskarupo23@gmail.com>
License-File: LICENSE
Classifier: License :: OSI Approved :: MIT License
Classifier: Operating System :: OS Independent
Classifier: Programming Language :: Python :: 3
Requires-Python: >=3.10.0
